<annotation>
	<folder>images</folder>
	<filename>sunplusit (670).jpg</filename>
	<path>D:\works\sunplusit_mask_indoor\images\sunplusit (670).jpg</path>
	<source>
		<database>Unknown</database>
	</source>
	<size>
		<width>3280</width>
		<height>1947</height>
		<depth>3</depth>
	</size>
	<segmented>0</segmented>
	<object>
		<name>bad</name>
		<pose>Unspecified</pose>
		<truncated>0</truncated>
		<difficult>0</difficult>
		<bndbox>
			<xmin>875</xmin>
			<ymin>501</ymin>
			<xmax>1062</xmax>
			<ymax>747</ymax>
		</bndbox>
	</object>
</annotation>
